{ "columns":0,
 "margin":0,
 "name":"ffs_new_teleport",
 "properties":
    {

    },
 "spacing":0,
 "tilecount":4,
 "tileheight":104,
 "tilewidth":316,
 "tileproperties":
    {
     "0":
        {
         "object":"ffs_movearrow_2_e",
         "tilesetDirection":"right"
		},
     "1":
        {
         "object":"ffs_movearrow_2_f",
         "tilesetDirection":"right"
		},
     "2":
        {
         "object":"ffs_movearrow_reverse_1",
         "tilesetDirection":"right"
		},
     "3":
        {
         "object":"ffs_mobileteleporter",
         "tilesetDirection":"right"
		}
    },
    
 "tiles":
    {
     "0":
        {
         "image":"ffs_movearrow.png"
        },
     "1":
        {
         "image":"ffs_movearrow.png"
        },
     "2":
        {
         "image":"ffs_movearrow_reverse.png"
        },
     "3":
        {
         "image":"ffs_mobileteleporter.png"
        }
    }
}